hms_utils/argv.py
hms_utils/aws/codebuild/utils.py
hms_utils/aws_ecs.py
hms_utils/aws_env.install.bash
hms_utils/aws_env.py
hms_utils/aws_env.sh
hms_utils/aws_url_accounting.py
hms_utils/aws_url_accounting_uniques.py
hms_utils/backup/hms_config_backup.py
hms_utils/chars.py
hms_utils/cli/crypt_cli.py
hms_utils/config/READmE
hms_utils/config/config.py
hms_utils/config/config_basic.py
hms_utils/config/config_cli.py
hms_utils/config/config_cli.sh
hms_utils/config/config_output.py
hms_utils/config/config_with_aws_macros.py
hms_utils/config/config_with_secrets.py
hms_utils/crypt_utils.py
hms_utils/datetime_utils.py
hms_utils/dbmi/portal_envs.py
hms_utils/dev/es-results.py
hms_utils/dev/recent_files_summary.py
hms_utils/dev/recent_files_summary_old.py
hms_utils/dev/recent_released_files.py
hms_utils/dev/work.py
hms_utils/dictionary_parented.py
hms_utils/dictionary_print_utils.py
hms_utils/dictionary_utils.py
hms_utils/elasticsearch_utils.py
hms_utils/env_utils.py
hms_utils/github_utils.py
hms_utils/hms_config.py
hms_utils/hms_config.sh
hms_utils/iterm/iterm_json_component.py
hms_utils/iterm/iterm_utc_clock.py
hms_utils/iterm/iterm_utils.py
hms_utils/misc_utils.py
hms_utils/path_utils.py
hms_utils/portal/indexing_status.py
hms_utils/portal/oneoff/check_for_duplicate_md5sum.py
hms_utils/portal/oneoff/portal_add_consortia_to_items.py
hms_utils/portal/oneoff/portal_items_without_consortia.py
hms_utils/portal/oneoff/portal_permissions_debugging.py
hms_utils/portal/oneoff/portal_submitted_file_summary.py
hms_utils/portal/oneoff/randomize_md5sum_values.py
hms_utils/portal/oneoff/sanity_check_smaht_users_spreadsheet.py
hms_utils/portal/portal_envs.py
hms_utils/portal/portal_files.py
hms_utils/portal/portal_generate_access_key.py
hms_utils/portal/portal_item_conflicts.py
hms_utils/portal/portal_permissions.py
hms_utils/portal/portal_read.py
hms_utils/portal/portal_reindex_items.py
hms_utils/portal/portal_simple_update.py
hms_utils/portal/portal_user_update.py
hms_utils-1.4.265.dist-info/LICENSE.txt
hms_utils-1.4.265.dist-info/METADATA
hms_utils-1.4.265.dist-info/WHEEL
hms_utils-1.4.265.dist-info/entry_points.txt
hms_utils-1.4.265.dist-info/RECORD
